__init__.py
base/__init__.py
base/dataframe.py
base/model.py
conformal/__init__.py
conformal/conformal_classifier.py
conformal_prediction_framework-0.1.1.dist-info/METADATA
conformal_prediction_framework-0.1.1.dist-info/WHEEL
conformal_prediction_framework-0.1.1.dist-info/top_level.txt
conformal_prediction_framework-0.1.1.dist-info/RECORD
