Metadata-Version: 2.4
Name: conformal-prediction-framework
Version: 0.1.1
Summary: A lightweight conformal prediction library built on top of scikit-learn.
Keywords: machine-learning,conformal-prediction,sklearn,uncertainty
Classifier: Programming Language :: Python :: 3
Classifier: License :: OSI Approved :: MIT License
Classifier: Development Status :: 3 - Alpha
Classifier: Intended Audience :: Developers
Classifier: Topic :: Scientific/Engineering :: Artificial Intelligence
Requires-Python: >=3.12
Requires-Dist: ipykernel>=6.29.5
Requires-Dist: lightgbm>=4.6.0
Requires-Dist: pandas==2.2.2
Requires-Dist: scikit-learn>=1.7.0
Requires-Dist: seaborn>=0.13.2
Requires-Dist: setuptools>=80.9.0
Requires-Dist: twine>=6.1.0
Requires-Dist: wheel>=0.45.1
Requires-Dist: xgboost>=3.0.2
